jitfields/__init__.py
jitfields/_regularisers_fields.py
jitfields/_regularisers_flows.py
jitfields/_version.py
jitfields/distance.py
jitfields/pushpull.py
jitfields/pushpull_backward.py
jitfields/regularisers.py
jitfields/resize.py
jitfields/splinc.py
jitfields/sym.py
jitfields/typing.py
jitfields/utils.py
jitfields/bindings/__init__.py
jitfields/bindings/common/__init__.py
jitfields/bindings/common/bounds.py
jitfields/bindings/common/resize.py
jitfields/bindings/common/splinc.py
jitfields/bindings/common/spline.py
jitfields/bindings/common/utils.py
jitfields/bindings/cpp/__init__.py
jitfields/bindings/cpp/distance.py
jitfields/bindings/cpp/pushpull.py
jitfields/bindings/cpp/regularisers.py
jitfields/bindings/cpp/resize.py
jitfields/bindings/cpp/restrict.py
jitfields/bindings/cpp/splinc.py
jitfields/bindings/cpp/sym.py
jitfields/bindings/cpp/threads.py
jitfields/bindings/cpp/utils.py
jitfields/bindings/cuda/__init__.py
jitfields/bindings/cuda/distance.py
jitfields/bindings/cuda/pushpull.py
jitfields/bindings/cuda/regularisers.py
jitfields/bindings/cuda/resize.py
jitfields/bindings/cuda/restrict.py
jitfields/bindings/cuda/splinc.py
jitfields/bindings/cuda/sym.py
jitfields/bindings/cuda/utils.py
jitfields/csrc/cpp/distance_euclidean.hpp
jitfields/csrc/cpp/distance_l1.hpp
jitfields/csrc/cpp/distance_mesh.hpp
jitfields/csrc/cpp/distance_spline.hpp
jitfields/csrc/cpp/posdef.hpp
jitfields/csrc/cpp/pushpull.hpp
jitfields/csrc/cpp/reg_field.hpp
jitfields/csrc/cpp/reg_flow.hpp
jitfields/csrc/cpp/resize.hpp
jitfields/csrc/cpp/restrict.hpp
jitfields/csrc/cpp/splinc.hpp
jitfields/csrc/cpp/tetrahedron.hpp
jitfields/csrc/cuda/distance_euclidean.cu
jitfields/csrc/cuda/distance_l1.cu
jitfields/csrc/cuda/distance_mesh.cu
jitfields/csrc/cuda/distance_spline.cu
jitfields/csrc/cuda/posdef.cu
jitfields/csrc/cuda/pushpull.cu
jitfields/csrc/cuda/reg_field.cu
jitfields/csrc/cuda/reg_flow.cu
jitfields/csrc/cuda/resize.cu
jitfields/csrc/cuda/restrict.cu
jitfields/csrc/cuda/splinc.cu
jitfields-0.1.0.dist-info/LICENSE
jitfields-0.1.0.dist-info/METADATA
jitfields-0.1.0.dist-info/WHEEL
jitfields-0.1.0.dist-info/top_level.txt
jitfields-0.1.0.dist-info/RECORD
