Metadata-Version: 2.1
Name: jitfields
Version: 0.1.0
Summary: Fast utilities for dense scalar and vector fields
Home-page: UNKNOWN
Author: Yael Balbastre
Author-email: yael.balbastre@gmail.com
License: MIT
Project-URL: Source Code, https://github.com/balbasty/jitfields
Platform: OS Independent
Classifier: License :: OSI Approved :: MIT License
Classifier: Operating System :: OS Independent
Classifier: Programming Language :: Python :: 3
Classifier: Intended Audience :: Science/Research
Classifier: Topic :: Scientific/Engineering :: Artificial Intelligence
Classifier: Topic :: Scientific/Engineering :: Medical Science Apps.
Requires-Python: >=3.6
Requires-Dist: numpy
Requires-Dist: cppyy
Requires-Dist: torch >=1.8
Provides-Extra: cuda
Requires-Dist: cupy ; extra == 'cuda'
Provides-Extra: test
Requires-Dist: pytest ; extra == 'test'
